telegram_exception_alerts/__init__.py
telegram_exception_alerts/alerter.py
telegram_exception_alerts-1.0.1.dist-info/WHEEL
telegram_exception_alerts-1.0.1.dist-info/METADATA
telegram_exception_alerts-1.0.1.dist-info/RECORD
