Metadata-Version: 2.1
Name: telegram-exception-alerts
Version: 1.0.1
Summary: 
Home-page: https://github.com/licht1stein/telegram-exception-alerts
License: MIT
Author: licht1stein
Author-email: mb@blaster.ai
Requires-Python: >=3.7,<4.0
Classifier: License :: OSI Approved :: MIT License
Classifier: Programming Language :: Python :: 3
Classifier: Programming Language :: Python :: 3.7
Classifier: Programming Language :: Python :: 3.8
Classifier: Programming Language :: Python :: 3.9
